Metadata-Version: 2.1
Name: streamlit_crud
Version: 0.1.61
Summary: Automatically generate UI components based on the data model, and implement CRUD functionalities.
Home-page: https://github.com/davidho123/streamlit-crud
Author: davidho
Author-email: 
License: MIT
Keywords: crud,streamlit,model,function,python
Classifier: Development Status :: 1 - Planning
Classifier: Intended Audience :: Developers
Classifier: Programming Language :: Python :: 3
License-File: LICENSE
